{
    "1": {
        "old": "0:00:00.0245518",
        "new": "",
        "old-no-dynamic": "0:00:00,0206545",
        "new-no-dynamic": ""
    },
    "100": {
        "old": "0:00:00.2913603",
        "new": "",
        "old-no-dynamic": "0:00:00.0555818",
        "new-no-dynamic": ""
    },
    "500": {
        "old": "0:00:01.4175398",
        "new": "",
        "old-no-dynamic": "0:00:00.2405773",
        "new-no-dynamic": ""
    },
    "1000": {
        "old": "0:00:02.8154299",
        "new": "",
        "old-no-dynamic": "0:00:00.4547153",
        "new-no-dynamic": ""
    },
    "5000": {
        "old": "0:00:13.9174308",
        "new": "",
        "old-no-dynamic": "0:00:02.2296616",
        "new-no-dynamic": ""
    }
}